fabric_rundeck/__init__.py
fabric_rundeck/__main__.py
fabric_rundeck/cron.py
fabric_rundeck/visitor.py
fabric_rundeck-1.2.dist-info/DESCRIPTION.rst
fabric_rundeck-1.2.dist-info/METADATA
fabric_rundeck-1.2.dist-info/pydist.json
fabric_rundeck-1.2.dist-info/RECORD
fabric_rundeck-1.2.dist-info/top_level.txt
fabric_rundeck-1.2.dist-info/WHEEL
