Metadata-Version: 2.0
Name: fabric-rundeck
Version: 1.2
Summary: Integration helpers for Fabric and Rundeck.
Home-page: http://github.com/coderanger/fabric-rundeck
Author: Noah Kantrowitz
Author-email: noah@coderanger.net
License: Apache 2.0
Platform: UNKNOWN
Classifier: Development Status :: 4 - Beta
Classifier: License :: OSI Approved :: Apache Software License
Classifier: Natural Language :: English
Classifier: Operating System :: OS Independent
Classifier: Programming Language :: Python
Requires-Dist: Fabric
